pycsvdb/CsvFileManage.py
pycsvdb/__init__.py
pycsvdb-1.7.dist-info/DESCRIPTION.rst
pycsvdb-1.7.dist-info/METADATA
pycsvdb-1.7.dist-info/RECORD
pycsvdb-1.7.dist-info/WHEEL
pycsvdb-1.7.dist-info/metadata.json
pycsvdb-1.7.dist-info/top_level.txt
pycsvmadeeasy/__init__.py
